meshtui/__init__.py
meshtui/__main__.py
meshtui/app.css
meshtui/app.py
meshtui/channel.py
meshtui/connection.py
meshtui/contact.py
meshtui/database.py
meshtui/room.py
meshtui/transport.py
meshtui/proxy/__init__.py
meshtui/proxy/__main__.py
meshtui/proxy/config.py
meshtui/proxy/proxy.py
meshtui/proxy/tcp_server.py
meshtui/proxy/backends/__init__.py
meshtui/proxy/backends/serial.py
meshtui-0.2.9.dist-info/METADATA
meshtui-0.2.9.dist-info/WHEEL
meshtui-0.2.9.dist-info/entry_points.txt
meshtui-0.2.9.dist-info/licenses/LICENSE
meshtui-0.2.9.dist-info/RECORD
