Metadata-Version: 2.4
Name: meshtui
Version: 0.2.9
Summary: Terminal User Interface for MeshCore companion radios
Project-URL: Homepage, https://ekollof.github.io/meshtui
Project-URL: Issues, https://github.com/ekollof/meshtui/issues
Project-URL: Repository, https://github.com/ekollof/meshtui
Author-email: Emiel Kollof <emiel@kollof.nl>
License-Expression: MIT
License-File: LICENSE
Keywords: lora,mesh,meshcore,radio,terminal,tui
Classifier: Development Status :: 4 - Beta
Classifier: Environment :: Console
Classifier: Intended Audience :: End Users/Desktop
Classifier: License :: OSI Approved :: MIT License
Classifier: Operating System :: OS Independent
Classifier: Programming Language :: Python :: 3
Classifier: Programming Language :: Python :: 3.10
Classifier: Programming Language :: Python :: 3.11
Classifier: Programming Language :: Python :: 3.12
Classifier: Programming Language :: Python :: 3.13
Classifier: Topic :: Communications :: Ham Radio
Classifier: Topic :: Terminals
Requires-Python: >=3.10
Requires-Dist: aiohttp>=3.9.0
Requires-Dist: dbus-python>=1.2.18
Requires-Dist: meshcore>=2.1.9
Requires-Dist: notify2>=0.3.1
Requires-Dist: requests>=2.28.0
Requires-Dist: textual>=0.50.0
Provides-Extra: dev
Requires-Dist: pytest-asyncio>=0.21.0; extra == 'dev'
Requires-Dist: pytest-cov>=4.0.0; extra == 'dev'
Requires-Dist: pytest-mock>=3.10.0; extra == 'dev'
Requires-Dist: pytest>=7.0.0; extra == 'dev'
Provides-Extra: proxy
Requires-Dist: pyserial-asyncio>=0.6; extra == 'proxy'
Requires-Dist: pyserial>=3.5; extra == 'proxy'
Requires-Dist: pyyaml>=6.0; extra == 'proxy'
